mesh_common/__init__.py
mesh_common/aws.py
mesh_common/concurrency.py
mesh_common/constants.py
mesh_common/encoding.py
mesh_common/env_config.py
mesh_common/fernet.py
mesh_common/fixtures.py
mesh_common/httpx_retry_transport.py
mesh_common/lambdas.py
mesh_common/oas.py
mesh_common/py.typed
mesh_common/singletons.py
mesh_common/sqs_helper.py
mesh_common/store.py
mesh_common/test_helpers.py
mesh_common/test_helpers_logs.py
mesh_common/text.py
mesh_common-0.2.7.dist-info/LICENSE.md
mesh_common-0.2.7.dist-info/METADATA
mesh_common-0.2.7.dist-info/WHEEL
mesh_common-0.2.7.dist-info/RECORD
