Metadata-Version: 2.1
Name: mesh-common
Version: 0.2.7
Summary: 
License: MIT
Author: spinecore
Requires-Python: >=3.10,<4.0
Classifier: License :: OSI Approved :: MIT License
Classifier: Programming Language :: Python :: 3
Classifier: Programming Language :: Python :: 3.10
Classifier: Programming Language :: Python :: 3.11
Requires-Dist: boto3 (>=1.26.159,<2.0.0)
Requires-Dist: boto3-stubs[dynamodb,events,lambda,logs,s3,secretsmanager,sns,sqs,ssm] (>=1.28.36,<2.0.0)
Requires-Dist: httpx (>=0.24.1,<0.25.0)
Requires-Dist: nhs-aws-helpers (>=0.3.2,<0.4.0)
Requires-Dist: nhs-context-logging (>=0.2.5,<0.3.0)
Requires-Dist: types-cryptography (>=3.3.23.2,<4.0.0.0)
Requires-Dist: types-python-dateutil (>=2.8.19.13,<3.0.0.0)
Requires-Dist: types-urllib3 (>=1.26.25.13,<2.0.0.0)
